README.rst
setup.cfg
setup.py
ddbpy3/__init__.py
ddbpy3/_version.py
ddbpy3/client.py
ddbpy3/dproto_hdr.py
ddbpy3/dproto_tcp.py
ddbpy3.egg-info/PKG-INFO
ddbpy3.egg-info/SOURCES.txt
ddbpy3.egg-info/dependency_links.txt
ddbpy3.egg-info/not-zip-safe
ddbpy3.egg-info/requires.txt
ddbpy3.egg-info/top_level.txt
test/__init__.py
test/listen.py
test/rand_test.py