Metadata-Version: 1.1
Name: ddbpy3
Version: 0.0.1
Summary: Dalmatiner Python 3 Client
Home-page: https://github.com/lucilecoutouly/ddbpy3
Author: Steven Acreman
Author-email: lucile.coutouly@obs-nancay.fr
License: Apache License, Version 2.0
Download-URL: https://github.com/lucilecoutouly/ddbpy3/tarball/v0.0.1
Keywords: dataloop dalmatiner
Platform: any
Classifier: Intended Audience :: Developers
Classifier: Intended Audience :: System Administrators
Classifier: License :: OSI Approved :: Apache Software License
